generative_agent/__init__.py
generative_agent/agent_state_memory.py
generative_agent/agent_types.py
generative_agent/custom_agents.py
generative_agent/database_connector.py
generative_agent/setup.py
generative_agent/time_weighted_retriever.py
generative_agent/tools.py
generative_agent/prompt/en_prompt.py
generative_agent/prompt/th_prompt.py
generative_agent-0.0.11.dist-info/METADATA
generative_agent-0.0.11.dist-info/WHEEL
generative_agent-0.0.11.dist-info/top_level.txt
generative_agent-0.0.11.dist-info/RECORD
