Metadata-Version: 2.1
Name: generative-agent
Version: 0.0.11
Summary: A package for generative agents
Home-page: https://github.com/MQDC-Tech/bel-generative-agents
Author: Donnaphat Trakulwaranont
Author-email: donnaphat_tr@dtgo.com
Classifier: Programming Language :: Python :: 3
Classifier: License :: OSI Approved :: MIT License
Classifier: Operating System :: OS Independent
Requires-Python: >=3.8.8
